[
    {
        "id": "rohandutta27102000@gmail.com",
        "password": "RDX",
        "auth": 2418
    },
    {
        "id": "gauravdutta1994@gmail.com",
        "password": "Gaurav",
        "auth": 2419
    },
    {
        "id": "gauravdutta@gmail.com",
        "password": "gauravdutta1111",
        "auth": 2420
    },
    {
        "id": "divyadutta@gmail.com",
        "password": "divya1234",
        "auth": 2421
    },
    {
        "id": "rakesh@gmail.com",
        "password": "@Godgift",
        "auth": 2422
    },
    {
        "id": "harry@gmail.com",
        "password": "codewithharry",
        "auth": 2423
    },
    {
        "id": "rdx@gmail.com",
        "password": "codewithRDX",
        "auth": 2424
    },
    {
        "id": "johncena@gmail.com",
        "password": "cenation",
        "auth": 2425
    },
    {
        "id": "brocklesnar@gmail.com",
        "password": "beast",
        "auth": 2426
    },
    {
        "id": "rdxboy@gmail.com",
        "password": "rohandutta",
        "auth": 2427
    },
    {
        "id": "priya@gmail.com",
        "password": "priya",
        "auth": 2428
    },
    {
        "id": "abd@gmail.com",
        "password": "abd1234",
        "auth": 2429
    },
    {
        "id": "tarun@gmail.com",
        "password": "tarun",
        "auth": 2430
    },
    {
        "id": "golu@gmail.com",
        "password": "golu123",
        "auth": 2431
    },
    {
        "id": "anany@gmail.com",
        "password": "anany",
        "auth": 2432
    }
]